chemicalconverters/__init__.py
chemicalconverters/model_utils/__init__.py
chemicalconverters/model_utils/config.py
chemicalconverters/model_utils/docstrings.py
chemicalconverters/model_utils/model.py
chemicalconverters/names_converters/__init__.py
chemicalconverters/names_converters/names_converters.py
chemical_converters-0.1.2.dist-info/METADATA
chemical_converters-0.1.2.dist-info/WHEEL
chemical_converters-0.1.2.dist-info/licenses/LICENSE
chemical_converters-0.1.2.dist-info/RECORD
